LICENSE.txt
README.md
setup.cfg
setup.py
clickhouse_cli/__init__.py
clickhouse_cli/cli.py
clickhouse_cli/clickhouse-cli.rc.sample
clickhouse_cli/config.py
clickhouse_cli/helpers.py
clickhouse_cli.egg-info/PKG-INFO
clickhouse_cli.egg-info/SOURCES.txt
clickhouse_cli.egg-info/dependency_links.txt
clickhouse_cli.egg-info/entry_points.txt
clickhouse_cli.egg-info/not-zip-safe
clickhouse_cli.egg-info/requires.txt
clickhouse_cli.egg-info/top_level.txt
clickhouse_cli/clickhouse/__init__.py
clickhouse_cli/clickhouse/client.py
clickhouse_cli/clickhouse/definitions.py
clickhouse_cli/clickhouse/exceptions.py
clickhouse_cli/clickhouse/sqlparse_patch.py
clickhouse_cli/ui/__init__.py
clickhouse_cli/ui/completer.py
clickhouse_cli/ui/lexer.py
clickhouse_cli/ui/prompt.py
clickhouse_cli/ui/style.py
clickhouse_cli/ui/parseutils/__init__.py
clickhouse_cli/ui/parseutils/ctes.py
clickhouse_cli/ui/parseutils/helpers.py
clickhouse_cli/ui/parseutils/meta.py
clickhouse_cli/ui/parseutils/tables.py
clickhouse_cli/ui/parseutils/utils.py