Metadata-Version: 2.1
Name: clickhouse-cli
Version: 0.3.9
Summary: A third-party client for the Clickhouse DBMS server.
Home-page: https://github.com/hatarist/clickhouse-cli
Author: Igor Hatarist
Author-email: igor@hatari.st
License: MIT
Keywords: clickhouse
License-File: LICENSE.txt
